nr/date/__init__.py
nr/date/duration.py
nr/date/format.py
nr/date/format_sets.py
nr/date/options.py
nr/date/py.typed
nr/date/re.py
nr_date-2.0.0.dist-info/LICENSE
nr_date-2.0.0.dist-info/WHEEL
nr_date-2.0.0.dist-info/METADATA
nr_date-2.0.0.dist-info/RECORD
